fastack_sqlmodel/__init__.py
fastack_sqlmodel/globals.py
fastack_sqlmodel/helpers.py
fastack_sqlmodel/models.py
fastack_sqlmodel/session.py
fastack_sqlmodel-0.4.1.dist-info/WHEEL
fastack_sqlmodel-0.4.1.dist-info/METADATA
fastack_sqlmodel-0.4.1.dist-info/RECORD
